i2cflash/__init__.py
i2cflash/serialeeprom.py
pyi2cflash-0.2.2.dist-info/LICENSE
pyi2cflash-0.2.2.dist-info/METADATA
pyi2cflash-0.2.2.dist-info/WHEEL
pyi2cflash-0.2.2.dist-info/top_level.txt
pyi2cflash-0.2.2.dist-info/RECORD
