Metadata-Version: 2.1
Name: pyi2cflash
Version: 0.2.2
Summary: I2C eeprom device drivers (pure Python)
Home-page: http://github.com/eblot/pyi2cflash
Author: Emmanuel Blot
Author-email: emmanuel.blot@free.fr
Maintainer: Emmanuel Blot
Maintainer-email: emmanuel.blot@free.fr
License: MIT
Keywords: driver,ftdi,usb,i2c,twi,flash,eeprom
Platform: UNKNOWN
Classifier: Development Status :: 3 - Alpha
Classifier: Environment :: Other Environment
Classifier: Natural Language :: English
Classifier: Intended Audience :: Developers
Classifier: License :: OSI Approved :: MIT License
Classifier: Operating System :: MacOS :: MacOS X
Classifier: Operating System :: POSIX
Classifier: Operating System :: Microsoft :: Windows
Classifier: Programming Language :: Python :: 3.5
Classifier: Programming Language :: Python :: 3.6
Classifier: Programming Language :: Python :: 3.7
Classifier: Programming Language :: Python :: 3.8
Classifier: Topic :: Software Development :: Libraries :: Python Modules
Classifier: Topic :: System :: Hardware :: Hardware Drivers
Requires-Python: >=3.5
Requires-Dist: pyftdi (<0.60,>=0.42)
